[
  {
    "id": "gh_astral-sh_ruff_22635",
    "title": "Handle markdown code blocks with syntax errors",
    "description": "Repository: astral-sh/ruff\nIssue #22635\n\nWarning, error, or diagnostic?",
    "repo": "astral-sh/ruff",
    "expected_labels": [],
    "complexity": "low",
    "source": "github"
  },
  {
    "id": "gh_astral-sh_ruff_22637",
    "title": "Skip directives for markdown formatting",
    "description": "Repository: astral-sh/ruff\nIssue #22637\n\nBlacken docs uses HTML comments: https://github.com/adamchainz/blacken-docs/#markdown\n\nDo we want something different? Should we support blacken docs' directives?",
    "repo": "astral-sh/ruff",
    "expected_labels": [],
    "complexity": "low",
    "source": "github"
  }
]